LICENSE
pytest_jinja/__init__.py
pytest_jinja/pytest_jinja.py
pytest_jinja/templates/bootstrap/bootstrap_template.html
pytest_jinja/templates/default/default.html
pytest_jinja/templates/default/main.js
pytest_jinja/templates/default/style.css
pytest_jinja-0.1.3.dist-info/entry_points.txt
pytest_jinja-0.1.3.dist-info/LICENSE
pytest_jinja-0.1.3.dist-info/WHEEL
pytest_jinja-0.1.3.dist-info/METADATA
pytest_jinja-0.1.3.dist-info/RECORD
