Metadata-Version: 2.1
Name: pytest-jinja
Version: 0.1.3
Summary: A plugin to generate customizable jinja-based HTML reports in pytest
Home-page: https://github.com/g-bon/pytest-jinja
License: GPL-2.0
Keywords: py.test,pytest,html,testing,report
Author: Gabriele Bonetti
Author-email: gabriele.bonetti@gmail.com
Requires-Python: >=3.7,<4.0
Classifier: Development Status :: 3 - Alpha
Classifier: Framework :: Pytest
Classifier: Intended Audience :: Developers
Classifier: License :: OSI Approved :: GNU General Public License v2 (GPLv2)
Classifier: License :: OSI Approved :: Mozilla Public License 2.0 (MPL 2.0)
Classifier: Operating System :: MacOS :: MacOS X
Classifier: Operating System :: Microsoft :: Windows
Classifier: Operating System :: POSIX
Classifier: Programming Language :: Python
Classifier: Programming Language :: Python :: 3
Classifier: Programming Language :: Python :: 3 :: Only
Classifier: Programming Language :: Python :: 3.10
Classifier: Programming Language :: Python :: 3.7
Classifier: Programming Language :: Python :: 3.8
Classifier: Programming Language :: Python :: 3.9
Classifier: Topic :: Software Development :: Quality Assurance
Classifier: Topic :: Software Development :: Testing
Classifier: Topic :: Utilities
Requires-Dist: jinja2
Requires-Dist: pytest (>=6.2.5,<7.0.0)
Requires-Dist: pytest-metadata
Project-URL: Repository, https://github.com/g-bon/pytest-jinja
